[
  {
    "index": 1,
    "verse_number": 1,
    "translation": "Ist zu dir die Geschichte der Überdeckenden gekommen?",
    "arabic": " هَلْ أَتَىٰكَ حَدِيثُ ٱلْغَـٰشِيَةِ",
    "transcription": "Hal atāka ḥadīṡul-gāsyiyah(ti)."
  },
  {
    "index": 2,
    "verse_number": 2,
    "translation": "(Die einen) Gesichter werden an jenem Tag demütig sein,",
    "arabic": "وُجُوهٌ يَوْمَئِذٍ خَـٰشِعَةٌ",
    "transcription": "Wujūhuy yauma'iżin khāsyi'ah(tun)."
  },
  {
    "index": 3,
    "verse_number": 3,
    "translation": "sich abarbeitend und von Mühsal erfüllt,",
    "arabic": "عَامِلَةٌ نَّاصِبَةٌ",
    "transcription": "'Amilatun nāṣibah(tun)."
  },
  {
    "index": 4,
    "verse_number": 4,
    "translation": "einem sehr heißen Feuer ausgesetzt,",
    "arabic": "تَصْلَىٰ نَارًا حَامِيَةً",
    "transcription": "Taṣlā nāran ḥāmiyah(tan)."
  },
  {
    "index": 5,
    "verse_number": 5,
    "translation": "und aus einer siedenden Quelle zu trinken bekommen.",
    "arabic": "تُسْقَىٰ مِنْ عَيْنٍ ءَانِيَةٍ",
    "transcription": "Tusqā min 'ainin āniyah(tin)."
  },
  {
    "index": 6,
    "verse_number": 6,
    "translation": "Es wird für sie keine Speise geben außer aus trockenen Dornen,",
    "arabic": "لَّيْسَ لَهُمْ طَعَامٌ إِلَّا مِن ضَرِيعٍ",
    "transcription": "Laisa lahum ṭa'āmun illā min ḍarī'(in)."
  },
  {
    "index": 7,
    "verse_number": 7,
    "translation": "die weder fett machen noch gegen den Hunger nützen.",
    "arabic": "لَّا يُسْمِنُ وَلَا يُغْنِى مِن جُوعٍ",
    "transcription": "Lā yusminu wa lā yugnī min jū'(in)."
  },
  {
    "index": 8,
    "verse_number": 8,
    "translation": "(Die anderen) Gesichter werden an jenem Tag wonnig sein,",
    "arabic": "وُجُوهٌ يَوْمَئِذٍ نَّاعِمَةٌ",
    "transcription": "Wujūhuy yauma'iżin nā'imah(tun)."
  },
  {
    "index": 9,
    "verse_number": 9,
    "translation": "mit ihrem Bemühen zufrieden",
    "arabic": "لِّسَعْيِهَا رَاضِيَةٌ",
    "transcription": "Lisa'yihā rāḍiyah(tun)."
  },
  {
    "index": 10,
    "verse_number": 10,
    "translation": "und in einem hohen Garten,",
    "arabic": "فِى جَنَّةٍ عَالِيَةٍ",
    "transcription": "Fī jannatin 'āliyah(tin)."
  },
  {
    "index": 11,
    "verse_number": 11,
    "translation": "worin sie keine unbedachte Rede hören.",
    "arabic": "لَّا تَسْمَعُ فِيهَا لَـٰغِيَةً",
    "transcription": "Lā tasama'u fīhā lāgiyah(tan)."
  },
  {
    "index": 12,
    "verse_number": 12,
    "translation": "Darin gibt es eine fließende Quelle,",
    "arabic": "فِيهَا عَيْنٌ جَارِيَةٌ",
    "transcription": "Fīhā 'ainun jāriyah(tun)."
  },
  {
    "index": 13,
    "verse_number": 13,
    "translation": "darin gibt es erhöhte Liegen",
    "arabic": "فِيهَا سُرُرٌ مَّرْفُوعَةٌ",
    "transcription": "Fīhā sururum marfū'ah(tun)."
  },
  {
    "index": 14,
    "verse_number": 14,
    "translation": "und hingestellte Trinkschalen",
    "arabic": "وَأَكْوَابٌ مَّوْضُوعَةٌ",
    "transcription": "Wa akwābum mauḍū'ah(tun)."
  },
  {
    "index": 15,
    "verse_number": 15,
    "translation": "und aufgereihte Kissen",
    "arabic": "وَنَمَارِقُ مَصْفُوفَةٌ",
    "transcription": "Wa namāriqu maṣfūfah(tun)."
  },
  {
    "index": 16,
    "verse_number": 16,
    "translation": "und ausgebreitete Teppiche.",
    "arabic": "وَزَرَابِىُّ مَبْثُوثَةٌ",
    "transcription": "Wa zarābiyyu mabṡūṡah(tun)."
  },
  {
    "index": 17,
    "verse_number": 17,
    "translation": "Schauen sie denn nicht zu den Kamelen, wie sie erschaffen worden sind,",
    "arabic": "أَفَلَا يَنظُرُونَ إِلَى ٱلْإِبِلِ كَيْفَ خُلِقَتْ",
    "transcription": "Afalā yanẓurūna ilal-ibili kaifa khuliqat."
  },
  {
    "index": 18,
    "verse_number": 18,
    "translation": "und zum Himmel, wie er emporgehoben worden ist,",
    "arabic": "وَإِلَى ٱلسَّمَآءِ كَيْفَ رُفِعَتْ",
    "transcription": "Wa ilas-samā'i kaifa rufi'at."
  },
  {
    "index": 19,
    "verse_number": 19,
    "translation": "und zu den Bergen, wie sie aufgerichtet worden sind,",
    "arabic": "وَإِلَى ٱلْجِبَالِ كَيْفَ نُصِبَتْ",
    "transcription": "Wa ilal-jibāli kaifa nuṣibat."
  },
  {
    "index": 20,
    "verse_number": 20,
    "translation": "und zur Erde, wie sie flach gemacht worden ist?",
    "arabic": "وَإِلَى ٱلْأَرْضِ كَيْفَ سُطِحَتْ",
    "transcription": "Wa ilal-arḍi kaifa suṭiḥat."
  },
  {
    "index": 21,
    "verse_number": 21,
    "translation": "So ermahne; du bist nur ein Ermahner.",
    "arabic": "فَذَكِّرْ إِنَّمَآ أَنتَ مُذَكِّرٌ",
    "transcription": "Fa żakkir, innamā anta mużakkir(un)."
  },
  {
    "index": 22,
    "verse_number": 22,
    "translation": "Du übst nicht die Oberherrschaft über sie aus.",
    "arabic": "لَّسْتَ عَلَيْهِم بِمُصَيْطِرٍ",
    "transcription": "Lasta 'alaihim bimusaiṭir(in)."
  },
  {
    "index": 23,
    "verse_number": 23,
    "translation": "Wer sich aber abkehrt und ungläubig ist,",
    "arabic": "إِلَّا مَن تَوَلَّىٰ وَكَفَرَ",
    "transcription": "Illā man tawallā wa kafar(a)."
  },
  {
    "index": 24,
    "verse_number": 24,
    "translation": "den straft dann Allah mit der größten Strafe.",
    "arabic": "فَيُعَذِّبُهُ ٱللَّهُ ٱلْعَذَابَ ٱلْأَكْبَرَ",
    "transcription": "Fa yu'ażżibuhullāhul-'ażābal-akbar(a)."
  },
  {
    "index": 25,
    "verse_number": 25,
    "translation": "Gewiß, zu Uns ist ihre Rückkehr",
    "arabic": "إِنَّ إِلَيْنَآ إِيَابَهُمْ",
    "transcription": "Inna ilainā iyābahum."
  },
  {
    "index": 26,
    "verse_number": 26,
    "translation": "und gewiß, hierauf obliegt Uns ihre Abrechnung.",
    "arabic": "ثُمَّ إِنَّ عَلَيْنَا حِسَابَهُم",
    "transcription": "Ṡumma inna 'alainā ḥisābahum."
  }
]