[
  {
    "index": 1,
    "verse_number": 1,
    "translation": "Ha-Mim.",
    "arabic_full": " حمٓ",
    "arabic": "",
    "transcription": "Ḥā mīm."
  },
  {
    "index": 2,
    "verse_number": 2,
    "translation": "(Dies ist) die Offenbarung des Buches von Allah, dem Allmächtigen und Allweisen.",
    "arabic_full": "تَنزِيلُ ٱلْكِتَـٰبِ مِنَ ٱللَّهِ ٱلْعَزِيزِ ٱلْحَكِيمِ",
    "arabic": "",
    "transcription": "Tanzīlul-kitābi minallāhil-'azīzil-ḥakīm(i)."
  },
  {
    "index": 3,
    "verse_number": 3,
    "translation": "In den Himmeln und auf der Erde sind wahrlich Zeichen für die Gläubigen.",
    "arabic_full": "إِنَّ فِى ٱلسَّمَـٰوَٰتِ وَٱلْأَرْضِ لَـَٔايَـٰتٍ لِّلْمُؤْمِنِينَ",
    "arabic": "",
    "transcription": "Inna fis-samāwāti wal-arḍi la'āyātil lil-mu'minīn(a)."
  },
  {
    "index": 4,
    "verse_number": 4,
    "translation": "Und in eurer Erschaffung und in dem, was Er an Tieren sich ausbreiten läßt, sind Zeichen für Leute, die überzeugt sind.",
    "arabic_full": "وَفِى خَلْقِكُمْ وَمَا يَبُثُّ مِن دَآبَّةٍ ءَايَـٰتٌ لِّقَوْمٍ يُوقِنُونَ",
    "arabic": "",
    "transcription": "Wa fī khalqikum wa mā yabuṡṡu min dābbatin āyātul liqaumiy yūqinūn(a)."
  },
  {
    "index": 5,
    "verse_number": 5,
    "translation": "Und (auch in) dem Unterschied von Nacht und Tag und (in) dem, was Allah an Versorgung vom Himmel herabkommen läßt",
    "arabic_full": "وَٱخْتِلَـٰفِ ٱلَّيْلِ وَٱلنَّهَارِ وَمَآ أَنزَلَ ٱللَّهُ مِنَ ٱلسَّمَآءِ مِن رِّزْقٍ فَأَحْيَا بِهِ ٱلْأَرْضَ بَعْدَ مَوْتِهَا وَتَصْرِيفِ ٱلرِّيَـٰحِ ءَايَـٰتٌ لِّقَوْمٍ يَعْقِلُونَ",
    "arabic": "",
    "transcription": "Wakhtilāfil-laili wan-nahāri wa mā anzalallāhu minas-samā'i mir rizqin"
  },
  {
    "index": 6,
    "verse_number": 5,
    "translation": "und dann damit die Erde nach ihrem Tod wieder lebendig macht, und im Wechsel der Winde sind Zeichen für Leute, die begreifen.",
    "arabic_full": "وَٱخْتِلَـٰفِ ٱلَّيْلِ وَٱلنَّهَارِ وَمَآ أَنزَلَ ٱللَّهُ مِنَ ٱلسَّمَآءِ مِن رِّزْقٍ فَأَحْيَا بِهِ ٱلْأَرْضَ بَعْدَ مَوْتِهَا وَتَصْرِيفِ ٱلرِّيَـٰحِ ءَايَـٰتٌ لِّقَوْمٍ يَعْقِلُونَ",
    "arabic": "",
    "transcription": "fa aḥyā bihil-arḍa ba'da mautihā wa taṣrīfir-riyāḥi āyātul liqaumiy ya'qilūn(a)."
  },
  {
    "index": 7,
    "verse_number": 6,
    "translation": "Dies sind Allahs Zeichen, die Wir dir der Wahrheit entsprechend verlesen.",
    "arabic_full": "تِلْكَ ءَايَـٰتُ ٱللَّهِ نَتْلُوهَا عَلَيْكَ بِٱلْحَقِّ ۖ فَبِأَىِّ حَدِيثٍۭ بَعْدَ ٱللَّهِ وَءَايَـٰتِهِۦ يُؤْمِنُونَ",
    "arabic": "",
    "transcription": "Tilka āyātullāhi natlūhā 'alaika bil-ḥaqq(i),"
  },
  {
    "index": 8,
    "verse_number": 6,
    "translation": "An welche Aussage nach (derjenigen) Allah(s) und Seinen Zeichen wollen sie denn (sonst) glauben?",
    "arabic_full": "تِلْكَ ءَايَـٰتُ ٱللَّهِ نَتْلُوهَا عَلَيْكَ بِٱلْحَقِّ ۖ فَبِأَىِّ حَدِيثٍۭ بَعْدَ ٱللَّهِ وَءَايَـٰتِهِۦ يُؤْمِنُونَ",
    "arabic": "",
    "transcription": "fa bi'ayyi ḥadīṡim ba'dallāhi wa āyātihī yu'minūn(a)."
  },
  {
    "index": 9,
    "verse_number": 7,
    "translation": "Wehe jedem durch und durch sündigen Lügner,",
    "arabic_full": "وَيْلٌ لِّكُلِّ أَفَّاكٍ أَثِيمٍ",
    "arabic": "",
    "transcription": "Wailul likulli affākin aṡīm(in)."
  },
  {
    "index": 10,
    "verse_number": 8,
    "translation": "der hört, wie ihm Allahs Zeichen verlesen werden, und hierauf hochmütig (in seinem Unglauben) verharrt, als ob er sie nicht gehört hätte!",
    "arabic_full": "يَسْمَعُ ءَايَـٰتِ ٱللَّهِ تُتْلَىٰ عَلَيْهِ ثُمَّ يُصِرُّ مُسْتَكْبِرًا كَأَن لَّمْ يَسْمَعْهَا ۖ فَبَشِّرْهُ بِعَذَابٍ أَلِيمٍ",
    "arabic": "",
    "transcription": "Yasma'u āyātillāhi tutlā 'alaihi ṡumma yuṣirru mustakbiran ka'allam yasma'hā,"
  },
  {
    "index": 11,
    "verse_number": 8,
    "translation": "So verkünde ihm schmerzhafte Strafe.",
    "arabic_full": "يَسْمَعُ ءَايَـٰتِ ٱللَّهِ تُتْلَىٰ عَلَيْهِ ثُمَّ يُصِرُّ مُسْتَكْبِرًا كَأَن لَّمْ يَسْمَعْهَا ۖ فَبَشِّرْهُ بِعَذَابٍ أَلِيمٍ",
    "arabic": "",
    "transcription": "fa basysyirhu bi'ażābin alīm(in)."
  },
  {
    "index": 12,
    "verse_number": 9,
    "translation": "Und wenn er etwas von Unseren Zeichen kennenlernt, macht er sich darüber lustig. Für solche wird es schmachvolle Strafe geben.",
    "arabic_full": "وَإِذَا عَلِمَ مِنْ ءَايَـٰتِنَا شَيْـًٔا ٱتَّخَذَهَا هُزُوًا ۚ أُو۟لَـٰٓئِكَ لَهُمْ عَذَابٌ مُّهِينٌ",
    "arabic": "",
    "transcription": "Wa iżā 'alima min āyātinā syai'anittakhażahā huzuwā(n), ulā'ika lahum 'ażābum muhīn(un)."
  },
  {
    "index": 13,
    "verse_number": 10,
    "translation": "Hinter ihnen (wartet) die Hölle. Und es nützt ihnen nicht, was sie erworben",
    "arabic_full": "مِّن وَرَآئِهِمْ جَهَنَّمُ ۖ وَلَا يُغْنِى عَنْهُم مَّا كَسَبُوا۟ شَيْـًٔا وَلَا مَا ٱتَّخَذُوا۟ مِن دُونِ ٱللَّهِ أَوْلِيَآءَ ۖ وَلَهُمْ عَذَابٌ عَظِيمٌ",
    "arabic": "",
    "transcription": "Miw warā'ihim jahannam(u), wa lā yugnī 'anhum mā kasabū"
  },
  {
    "index": 14,
    "verse_number": 10,
    "translation": "und (auch) nicht, was sie sich anstatt Allahs zu Schutzherren genommen haben; für sie wird es gewaltige Strafe geben.",
    "arabic_full": "مِّن وَرَآئِهِمْ جَهَنَّمُ ۖ وَلَا يُغْنِى عَنْهُم مَّا كَسَبُوا۟ شَيْـًٔا وَلَا مَا ٱتَّخَذُوا۟ مِن دُونِ ٱللَّهِ أَوْلِيَآءَ ۖ وَلَهُمْ عَذَابٌ عَظِيمٌ",
    "arabic": "",
    "transcription": "wa lā mattakhażū min dūnillāhi auliyā'(a), wa lahum 'ażābun 'aẓīm(un)."
  },
  {
    "index": 15,
    "verse_number": 11,
    "translation": "Dies ist eine Rechtleitung. Und diejenigen, die die Zeichen ihres Herrn verleugnen, für sie wird es schmerzhafte Strafe von Züchtigung geben.",
    "arabic_full": "هَـٰذَا هُدًى ۖ وَٱلَّذِينَ كَفَرُوا۟ بِـَٔايَـٰتِ رَبِّهِمْ لَهُمْ عَذَابٌ مِّن رِّجْزٍ أَلِيمٌ",
    "arabic": "",
    "transcription": "Hāżā hudā(n), wal-lażīna kafarū bi'āyāti rabbihim lahum 'ażābum mir rijzin alīm(un)."
  },
  {
    "index": 16,
    "verse_number": 12,
    "translation": "Allah ist es, Der euch das Meer dienstbar gemacht hat, damit die Schiffe darauf auf Seinen Befehl fahren",
    "arabic_full": "۞ ٱللَّهُ ٱلَّذِى سَخَّرَ لَكُمُ ٱلْبَحْرَ لِتَجْرِىَ ٱلْفُلْكُ فِيهِ بِأَمْرِهِۦ وَلِتَبْتَغُوا۟ مِن فَضْلِهِۦ وَلَعَلَّكُمْ تَشْكُرُونَ",
    "arabic": "",
    "transcription": "Allāhul-lażī sakhkhara lakumul-baḥra litajriyal-fulku fīhi bi'amrihī"
  },
  {
    "index": 17,
    "verse_number": 12,
    "translation": "und damit ihr nach etwas von Seiner Huld trachtet, und auf daß ihr dankbar sein möget.",
    "arabic_full": "۞ ٱللَّهُ ٱلَّذِى سَخَّرَ لَكُمُ ٱلْبَحْرَ لِتَجْرِىَ ٱلْفُلْكُ فِيهِ بِأَمْرِهِۦ وَلِتَبْتَغُوا۟ مِن فَضْلِهِۦ وَلَعَلَّكُمْ تَشْكُرُونَ",
    "arabic": "",
    "transcription": "wa litabtagū min faḍlihī wa la'allakum tasykurūn(a)."
  },
  {
    "index": 18,
    "verse_number": 13,
    "translation": "Und Er hat euch alles, was in den Himmeln und was auf der Erde ist, dienstbar gemacht, alles von Sich aus.",
    "arabic_full": "وَسَخَّرَ لَكُم مَّا فِى ٱلسَّمَـٰوَٰتِ وَمَا فِى ٱلْأَرْضِ جَمِيعًا مِّنْهُ ۚ إِنَّ فِى ذَٰلِكَ لَـَٔايَـٰتٍ لِّقَوْمٍ يَتَفَكَّرُونَ",
    "arabic": "",
    "transcription": "Wa sakhkhara lakum mā fis-samāwāti wa mā fil-arḍi jamī'am minh(u),"
  },
  {
    "index": 19,
    "verse_number": 13,
    "translation": "Darin sind wahrlich Zeichen für Leute, die nachdenken.",
    "arabic_full": "وَسَخَّرَ لَكُم مَّا فِى ٱلسَّمَـٰوَٰتِ وَمَا فِى ٱلْأَرْضِ جَمِيعًا مِّنْهُ ۚ إِنَّ فِى ذَٰلِكَ لَـَٔايَـٰتٍ لِّقَوْمٍ يَتَفَكَّرُونَ",
    "arabic": "",
    "transcription": "inna fī żālika la'āyātil liqaumiy yatafakkarūn(a)."
  },
  {
    "index": 20,
    "verse_number": 14,
    "translation": "Sag zu denjenigen, die glauben, sie sollen denjenigen vergeben, die nicht Allahs Tage erhoffen, auf daß Er einem (jeden) Volk das vergelte,",
    "arabic_full": "قُل لِّلَّذِينَ ءَامَنُوا۟ يَغْفِرُوا۟ لِلَّذِينَ لَا يَرْجُونَ أَيَّامَ ٱللَّهِ لِيَجْزِىَ قَوْمًۢا بِمَا كَانُوا۟ يَكْسِبُونَ",
    "arabic": "",
    "transcription": "Qul lil-lażīna āmanū yagfirū lil-lażīna lā yarjūna ayyāmallāhi liyajziya qaumam"
  },
  {
    "index": 21,
    "verse_number": 14,
    "translation": "was sie erworben haben.",
    "arabic_full": "قُل لِّلَّذِينَ ءَامَنُوا۟ يَغْفِرُوا۟ لِلَّذِينَ لَا يَرْجُونَ أَيَّامَ ٱللَّهِ لِيَجْزِىَ قَوْمًۢا بِمَا كَانُوا۟ يَكْسِبُونَ",
    "arabic": "",
    "transcription": "bimā kānū yaksibūn(a)."
  },
  {
    "index": 22,
    "verse_number": 15,
    "translation": "Wer rechtschaffen handelt, der (tut es) zu seinem eigenen Vorteil, und wer Böses tut, der (tut es) zu seinem eigenen Nachteil.",
    "arabic_full": "مَنْ عَمِلَ صَـٰلِحًا فَلِنَفْسِهِۦ ۖ وَمَنْ أَسَآءَ فَعَلَيْهَا ۖ ثُمَّ إِلَىٰ رَبِّكُمْ تُرْجَعُونَ",
    "arabic": "",
    "transcription": "Man 'amila ṣāliḥan fa linafsih(ī), wa man asā'a fa 'alaihā,"
  },
  {
    "index": 23,
    "verse_number": 15,
    "translation": "Hierauf werdet ihr zu eurem Herrn zurückgebracht.",
    "arabic_full": "مَنْ عَمِلَ صَـٰلِحًا فَلِنَفْسِهِۦ ۖ وَمَنْ أَسَآءَ فَعَلَيْهَا ۖ ثُمَّ إِلَىٰ رَبِّكُمْ تُرْجَعُونَ",
    "arabic": "",
    "transcription": "ṡumma ilā rabbikum turja'ūn(a)."
  },
  {
    "index": 24,
    "verse_number": 16,
    "translation": "Wir gaben ja den Kindern Isra’ils die Schrift, das Urteil und das Prophetentum und versorgten sie von den guten Dingen",
    "arabic_full": "وَلَقَدْ ءَاتَيْنَا بَنِىٓ إِسْرَٰٓءِيلَ ٱلْكِتَـٰبَ وَٱلْحُكْمَ وَٱلنُّبُوَّةَ وَرَزَقْنَـٰهُم مِّنَ ٱلطَّيِّبَـٰتِ وَفَضَّلْنَـٰهُمْ عَلَى ٱلْعَـٰلَمِينَ",
    "arabic": "",
    "transcription": "Wa laqad ātainā banī isrā'īlal-kitāba wal-ḥukma wan-nubuwwata wa razaqnāhum minaṭ-ṭayyibāti"
  },
  {
    "index": 25,
    "verse_number": 16,
    "translation": "und bevorzugten sie vor den (anderen) Weltenbewohnern.",
    "arabic_full": "وَلَقَدْ ءَاتَيْنَا بَنِىٓ إِسْرَٰٓءِيلَ ٱلْكِتَـٰبَ وَٱلْحُكْمَ وَٱلنُّبُوَّةَ وَرَزَقْنَـٰهُم مِّنَ ٱلطَّيِّبَـٰتِ وَفَضَّلْنَـٰهُمْ عَلَى ٱلْعَـٰلَمِينَ",
    "arabic": "",
    "transcription": "wa faḍḍalnāhum 'alal-'ālamīn(a)."
  },
  {
    "index": 26,
    "verse_number": 17,
    "translation": "Und Wir gaben ihnen klare Beweise in der Angelegenheit (der Religion).",
    "arabic_full": "وَءَاتَيْنَـٰهُم بَيِّنَـٰتٍ مِّنَ ٱلْأَمْرِ ۖ فَمَا ٱخْتَلَفُوٓا۟ إِلَّا مِنۢ بَعْدِ مَا جَآءَهُمُ ٱلْعِلْمُ بَغْيًۢا بَيْنَهُمْ ۚ إِنَّ رَبَّكَ يَقْضِى بَيْنَهُمْ يَوْمَ ٱلْقِيَـٰمَةِ فِيمَا كَانُوا۟ فِيهِ يَخْتَلِفُونَ",
    "arabic": "",
    "transcription": "Wa ātaināhum bayyinātim minal-amr(i),"
  },
  {
    "index": 27,
    "verse_number": 17,
    "translation": "Sie wurden aber erst uneinig, nachdem das Wissen zu ihnen gekommen war - aus Mißgunst untereinander.",
    "arabic_full": "وَءَاتَيْنَـٰهُم بَيِّنَـٰتٍ مِّنَ ٱلْأَمْرِ ۖ فَمَا ٱخْتَلَفُوٓا۟ إِلَّا مِنۢ بَعْدِ مَا جَآءَهُمُ ٱلْعِلْمُ بَغْيًۢا بَيْنَهُمْ ۚ إِنَّ رَبَّكَ يَقْضِى بَيْنَهُمْ يَوْمَ ٱلْقِيَـٰمَةِ فِيمَا كَانُوا۟ فِيهِ يَخْتَلِفُونَ",
    "arabic": "",
    "transcription": "fa makhtalafū illā mim ba'di mā jā'ahumul-'ilmu bagyam bainahum,"
  },
  {
    "index": 28,
    "verse_number": 17,
    "translation": "Gewiß, dein Herr wird am Tag der Auferstehung zwischen ihnen über das entscheiden, worüber sie uneinig zu sein pflegten.",
    "arabic_full": "وَءَاتَيْنَـٰهُم بَيِّنَـٰتٍ مِّنَ ٱلْأَمْرِ ۖ فَمَا ٱخْتَلَفُوٓا۟ إِلَّا مِنۢ بَعْدِ مَا جَآءَهُمُ ٱلْعِلْمُ بَغْيًۢا بَيْنَهُمْ ۚ إِنَّ رَبَّكَ يَقْضِى بَيْنَهُمْ يَوْمَ ٱلْقِيَـٰمَةِ فِيمَا كَانُوا۟ فِيهِ يَخْتَلِفُونَ",
    "arabic": "",
    "transcription": "inna rabbaka yaqḍī bainahum yaumal-qiyāmati fīmā kānū fīhi yakhtalifūn(a)."
  },
  {
    "index": 29,
    "verse_number": 18,
    "translation": "Hierauf haben Wir dich auf eine Richtung in der Angelegenheit (der Religion) festgelegt.",
    "arabic_full": "ثُمَّ جَعَلْنَـٰكَ عَلَىٰ شَرِيعَةٍ مِّنَ ٱلْأَمْرِ فَٱتَّبِعْهَا وَلَا تَتَّبِعْ أَهْوَآءَ ٱلَّذِينَ لَا يَعْلَمُونَ",
    "arabic": "",
    "transcription": "Ṡumma ja'alnāka 'alā syarī'atim minal-amri"
  },
  {
    "index": 30,
    "verse_number": 18,
    "translation": "So folge ihr und folge nicht den Neigungen derjenigen, die nicht Bescheid wissen.",
    "arabic_full": "ثُمَّ جَعَلْنَـٰكَ عَلَىٰ شَرِيعَةٍ مِّنَ ٱلْأَمْرِ فَٱتَّبِعْهَا وَلَا تَتَّبِعْ أَهْوَآءَ ٱلَّذِينَ لَا يَعْلَمُونَ",
    "arabic": "",
    "transcription": "fattabi'hā wa lā tattabi' ahwā'al-lażīna lā ya'lamūn(a)."
  },
  {
    "index": 31,
    "verse_number": 19,
    "translation": "Gewiß, sie werden dir vor Allah nichts nützen. Aber gewiß, die Ungerechten sind einer des anderen Schutzherren.",
    "arabic_full": "إِنَّهُمْ لَن يُغْنُوا۟ عَنكَ مِنَ ٱللَّهِ شَيْـًٔا ۚ وَإِنَّ ٱلظَّـٰلِمِينَ بَعْضُهُمْ أَوْلِيَآءُ بَعْضٍ ۖ وَٱللَّهُ وَلِىُّ ٱلْمُتَّقِينَ",
    "arabic": "",
    "transcription": "Innahum lay yugnū 'anka minallāhi syai'ā(n), wa innaẓ-ẓālimīna ba'ḍuhum auliyā'u ba'ḍ(in)."
  },
  {
    "index": 32,
    "verse_number": 19,
    "translation": "Allah aber ist der Schutzherr der Gottesfürchtigen.",
    "arabic_full": "إِنَّهُمْ لَن يُغْنُوا۟ عَنكَ مِنَ ٱللَّهِ شَيْـًٔا ۚ وَإِنَّ ٱلظَّـٰلِمِينَ بَعْضُهُمْ أَوْلِيَآءُ بَعْضٍ ۖ وَٱللَّهُ وَلِىُّ ٱلْمُتَّقِينَ",
    "arabic": "",
    "transcription": "wallāhu waliyyul-muttaqīn(a)."
  },
  {
    "index": 33,
    "verse_number": 20,
    "translation": "Dies sind einsichtbringende Zeichen für die Menschen und Rechtleitung und Barmherzigkeit für Leute, die überzeugt sind.",
    "arabic_full": "هَـٰذَا بَصَـٰٓئِرُ لِلنَّاسِ وَهُدًى وَرَحْمَةٌ لِّقَوْمٍ يُوقِنُونَ",
    "arabic": "",
    "transcription": "Hāżā baṣā'iru lin-nāsi wa hudaw wa raḥmatul liqaumiy yūqinūn(a)."
  },
  {
    "index": 34,
    "verse_number": 21,
    "translation": "Oder meinen diejenigen, die böse Taten verüben, daß Wir sie denjenigen, die glauben",
    "arabic_full": "أَمْ حَسِبَ ٱلَّذِينَ ٱجْتَرَحُوا۟ ٱلسَّيِّـَٔاتِ أَن نَّجْعَلَهُمْ كَٱلَّذِينَ ءَامَنُوا۟ وَعَمِلُوا۟ ٱلصَّـٰلِحَـٰتِ سَوَآءً مَّحْيَاهُمْ وَمَمَاتُهُمْ ۚ سَآءَ مَا يَحْكُمُونَ",
    "arabic": "",
    "transcription": "Am ḥasibal-lażīnajtaraḥus -sayyi'āti an naj'alahum kal-lażīna āmanū"
  },
  {
    "index": 35,
    "verse_number": 21,
    "translation": "und rechtschaffene Werke tun, gleichstellen sowohl in ihrem Leben als in ihrem Tod? Wie böse ist, was sie urteilen!",
    "arabic_full": "أَمْ حَسِبَ ٱلَّذِينَ ٱجْتَرَحُوا۟ ٱلسَّيِّـَٔاتِ أَن نَّجْعَلَهُمْ كَٱلَّذِينَ ءَامَنُوا۟ وَعَمِلُوا۟ ٱلصَّـٰلِحَـٰتِ سَوَآءً مَّحْيَاهُمْ وَمَمَاتُهُمْ ۚ سَآءَ مَا يَحْكُمُونَ",
    "arabic": "",
    "transcription": "wa 'amiluṣ-ṣāliḥāti sawā'am maḥyāhum wa mamātuhum, sā'a mā yaḥkumūn(a)."
  },
  {
    "index": 36,
    "verse_number": 22,
    "translation": "Und Allah hat die Himmel und die Erde in Wahrheit erschaffen, und damit jeder Seele das vergolten wird, was sie erworben hat,",
    "arabic_full": "وَخَلَقَ ٱللَّهُ ٱلسَّمَـٰوَٰتِ وَٱلْأَرْضَ بِٱلْحَقِّ وَلِتُجْزَىٰ كُلُّ نَفْسٍۭ بِمَا كَسَبَتْ وَهُمْ لَا يُظْلَمُونَ",
    "arabic": "",
    "transcription": "Wa khalaqallāhus-samāwāti wal-arḍa bil-ḥaqqi wa litujzā kullu nafsim bimā kasabat"
  },
  {
    "index": 37,
    "verse_number": 22,
    "translation": "und es wird ihnen kein Unrecht zugefügt.",
    "arabic_full": "وَخَلَقَ ٱللَّهُ ٱلسَّمَـٰوَٰتِ وَٱلْأَرْضَ بِٱلْحَقِّ وَلِتُجْزَىٰ كُلُّ نَفْسٍۭ بِمَا كَسَبَتْ وَهُمْ لَا يُظْلَمُونَ",
    "arabic": "",
    "transcription": "wa hum lā yuẓlamūn(a)."
  },
  {
    "index": 38,
    "verse_number": 23,
    "translation": "Was meinst du wohl zu jemandem, der sich als seinen Gott seine Neigung genommen hat, den Allah trotz (seines) Wissens hat in die Irre gehen lassen",
    "arabic_full": "أَفَرَءَيْتَ مَنِ ٱتَّخَذَ إِلَـٰهَهُۥ هَوَىٰهُ وَأَضَلَّهُ ٱللَّهُ عَلَىٰ عِلْمٍ وَخَتَمَ عَلَىٰ سَمْعِهِۦ وَقَلْبِهِۦ وَجَعَلَ عَلَىٰ بَصَرِهِۦ غِشَـٰوَةً فَمَن يَهْدِيهِ مِنۢ بَعْدِ ٱللَّهِ ۚ أَفَلَا تَذَكَّرُونَ",
    "arabic": "",
    "transcription": "Afa ra'aita manittakhaża ilāhahū hawāhu wa aḍallahullāhu 'alā 'ilmiw"
  },
  {
    "index": 39,
    "verse_number": 23,
    "translation": "und dem Er das Gehör und das Herz versiegelt und auf dessen Augenlicht eine Hülle gelegt hat?",
    "arabic_full": "أَفَرَءَيْتَ مَنِ ٱتَّخَذَ إِلَـٰهَهُۥ هَوَىٰهُ وَأَضَلَّهُ ٱللَّهُ عَلَىٰ عِلْمٍ وَخَتَمَ عَلَىٰ سَمْعِهِۦ وَقَلْبِهِۦ وَجَعَلَ عَلَىٰ بَصَرِهِۦ غِشَـٰوَةً فَمَن يَهْدِيهِ مِنۢ بَعْدِ ٱللَّهِ ۚ أَفَلَا تَذَكَّرُونَ",
    "arabic": "",
    "transcription": "wa khatama 'alā sam'ihī wa qalbihī wa ja'ala 'alā baṣarihī gisyāwah(tan)"
  },
  {
    "index": 40,
    "verse_number": 23,
    "translation": "Wer könnte ihn nach Allah rechtleiten? Bedenkt ihr denn nicht?",
    "arabic_full": "أَفَرَءَيْتَ مَنِ ٱتَّخَذَ إِلَـٰهَهُۥ هَوَىٰهُ وَأَضَلَّهُ ٱللَّهُ عَلَىٰ عِلْمٍ وَخَتَمَ عَلَىٰ سَمْعِهِۦ وَقَلْبِهِۦ وَجَعَلَ عَلَىٰ بَصَرِهِۦ غِشَـٰوَةً فَمَن يَهْدِيهِ مِنۢ بَعْدِ ٱللَّهِ ۚ أَفَلَا تَذَكَّرُونَ",
    "arabic": "",
    "transcription": "famay yahdīhi mim ba'dillāh(i), afalā tażakkarūn(a)."
  },
  {
    "index": 41,
    "verse_number": 24,
    "translation": "Und sie sagen: Es gibt nur unser diesseitiges Leben; wir sterben und leben, und nur die Zeiten vernichten uns.",
    "arabic_full": "وَقَالُوا۟ مَا هِىَ إِلَّا حَيَاتُنَا ٱلدُّنْيَا نَمُوتُ وَنَحْيَا وَمَا يُهْلِكُنَآ إِلَّا ٱلدَّهْرُ ۚ وَمَا لَهُم بِذَٰلِكَ مِنْ عِلْمٍ ۖ إِنْ هُمْ إِلَّا يَظُنُّونَ",
    "arabic": "",
    "transcription": "Wa qālū mā hiya illā ḥayātunad-dun-yā namūtu wa naḥyā wa mā yuhlikunā illad-dahr(u),"
  },
  {
    "index": 42,
    "verse_number": 24,
    "translation": "Sie haben (aber) kein Wissen davon, sie stellen nur Mutmaßungen an.",
    "arabic_full": "وَقَالُوا۟ مَا هِىَ إِلَّا حَيَاتُنَا ٱلدُّنْيَا نَمُوتُ وَنَحْيَا وَمَا يُهْلِكُنَآ إِلَّا ٱلدَّهْرُ ۚ وَمَا لَهُم بِذَٰلِكَ مِنْ عِلْمٍ ۖ إِنْ هُمْ إِلَّا يَظُنُّونَ",
    "arabic": "",
    "transcription": "wa mā lahum biżālika min 'ilmin in hum illā yaẓunnūn(a)."
  },
  {
    "index": 43,
    "verse_number": 25,
    "translation": "Und wenn ihnen Unsere Zeichen als klare Beweise verlesen werden, ist ihre Beweisgrundlage nur, daß sie sagen: Bringt unsere Väter herbei, wenn",
    "arabic_full": "وَإِذَا تُتْلَىٰ عَلَيْهِمْ ءَايَـٰتُنَا بَيِّنَـٰتٍ مَّا كَانَ حُجَّتَهُمْ إِلَّآ أَن قَالُوا۟ ٱئْتُوا۟ بِـَٔابَآئِنَآ إِن كُنتُمْ صَـٰدِقِينَ",
    "arabic": "",
    "transcription": "Wa iżā tutlā 'alaihim āyātunā bayyinātim mā kāna ḥujjatahum illā an qālu'tū bi'ābā'inā in kuntum"
  },
  {
    "index": 44,
    "verse_number": 25,
    "translation": "ihr wahrhaftig seid.",
    "arabic_full": "وَإِذَا تُتْلَىٰ عَلَيْهِمْ ءَايَـٰتُنَا بَيِّنَـٰتٍ مَّا كَانَ حُجَّتَهُمْ إِلَّآ أَن قَالُوا۟ ٱئْتُوا۟ بِـَٔابَآئِنَآ إِن كُنتُمْ صَـٰدِقِينَ",
    "arabic": "",
    "transcription": "in kuntum ṣādiqīn(a)."
  },
  {
    "index": 45,
    "verse_number": 26,
    "translation": "Sag: Allah macht euch lebendig und läßt euch hierauf sterben;",
    "arabic_full": "قُلِ ٱللَّهُ يُحْيِيكُمْ ثُمَّ يُمِيتُكُمْ ثُمَّ يَجْمَعُكُمْ إِلَىٰ يَوْمِ ٱلْقِيَـٰمَةِ لَا رَيْبَ فِيهِ وَلَـٰكِنَّ أَكْثَرَ ٱلنَّاسِ لَا يَعْلَمُونَ",
    "arabic": "",
    "transcription": "Qulillāhu yuḥyīkum yuḥyīkum ṡumma yumītukum"
  },
  {
    "index": 46,
    "verse_number": 26,
    "translation": "hierauf wird Er euch zum Tag der Auferstehung versammeln, an dem es keinen Zweifel gibt.",
    "arabic_full": "قُلِ ٱللَّهُ يُحْيِيكُمْ ثُمَّ يُمِيتُكُمْ ثُمَّ يَجْمَعُكُمْ إِلَىٰ يَوْمِ ٱلْقِيَـٰمَةِ لَا رَيْبَ فِيهِ وَلَـٰكِنَّ أَكْثَرَ ٱلنَّاسِ لَا يَعْلَمُونَ",
    "arabic": "",
    "transcription": "ṡumma yajma'ukum ilā yaumil-qiyāmati lā raiba fīhi"
  },
  {
    "index": 47,
    "verse_number": 26,
    "translation": "Aber die meisten Menschen wissen nicht.",
    "arabic_full": "قُلِ ٱللَّهُ يُحْيِيكُمْ ثُمَّ يُمِيتُكُمْ ثُمَّ يَجْمَعُكُمْ إِلَىٰ يَوْمِ ٱلْقِيَـٰمَةِ لَا رَيْبَ فِيهِ وَلَـٰكِنَّ أَكْثَرَ ٱلنَّاسِ لَا يَعْلَمُونَ",
    "arabic": "",
    "transcription": "wa lākinna akṡaran-nāsi lā ya'lamūn(a)."
  },
  {
    "index": 48,
    "verse_number": 27,
    "translation": "Allah gehört die Herrschaft der Himmel und der Erde.",
    "arabic_full": "وَلِلَّهِ مُلْكُ ٱلسَّمَـٰوَٰتِ وَٱلْأَرْضِ ۚ وَيَوْمَ تَقُومُ ٱلسَّاعَةُ يَوْمَئِذٍ يَخْسَرُ ٱلْمُبْطِلُونَ",
    "arabic": "",
    "transcription": "Wa lillāhi mulkus-samāwāti wal-arḍ(i),"
  },
  {
    "index": 49,
    "verse_number": 27,
    "translation": "Und am Tag, da sich die Stunde erhebt, an jenem Tag werden diejenigen verlieren, die Nichtiges tun.",
    "arabic_full": "وَلِلَّهِ مُلْكُ ٱلسَّمَـٰوَٰتِ وَٱلْأَرْضِ ۚ وَيَوْمَ تَقُومُ ٱلسَّاعَةُ يَوْمَئِذٍ يَخْسَرُ ٱلْمُبْطِلُونَ",
    "arabic": "",
    "transcription": "wa yauma taqūmus-sā'atu yauma'iżiy yakhsarul-mubṭilūn(a)."
  },
  {
    "index": 50,
    "verse_number": 28,
    "translation": "Und du wirst jede Gemeinschaft kniend sehen.",
    "arabic_full": "وَتَرَىٰ كُلَّ أُمَّةٍ جَاثِيَةً ۚ كُلُّ أُمَّةٍ تُدْعَىٰٓ إِلَىٰ كِتَـٰبِهَا ٱلْيَوْمَ تُجْزَوْنَ مَا كُنتُمْ تَعْمَلُونَ",
    "arabic": "",
    "transcription": "Wa tarā kulla ummatin jāṡiyah(tan),"
  },
  {
    "index": 51,
    "verse_number": 28,
    "translation": "Jede Gemeinschaft wird zu ihrem Buch gerufen: Heute wird euch das vergolten, was ihr zu tun pflegtet.",
    "arabic_full": "وَتَرَىٰ كُلَّ أُمَّةٍ جَاثِيَةً ۚ كُلُّ أُمَّةٍ تُدْعَىٰٓ إِلَىٰ كِتَـٰبِهَا ٱلْيَوْمَ تُجْزَوْنَ مَا كُنتُمْ تَعْمَلُونَ",
    "arabic": "",
    "transcription": "kullu ummatin tud'ā ilā kitābihā, al-yauma tujzauna mā kuntum ta'malūn(a)."
  },
  {
    "index": 52,
    "verse_number": 29,
    "translation": "Dies ist Unser Buch, das mit der Wahrheit gegen euch spricht. Wir ließen (alles) niederschreiben, was ihr zu tun pflegtet.",
    "arabic_full": "هَـٰذَا كِتَـٰبُنَا يَنطِقُ عَلَيْكُم بِٱلْحَقِّ ۚ إِنَّا كُنَّا نَسْتَنسِخُ مَا كُنتُمْ تَعْمَلُونَ",
    "arabic": "",
    "transcription": "Hāżā kitābunā yanṭiqu 'alaikum bil-ḥaqq(i), innā kunnā nastansikhu mā kuntum ta'malūn(a)."
  },
  {
    "index": 53,
    "verse_number": 30,
    "translation": "Was nun diejenigen angeht, die geglaubt und rechtschaffene Werke getan haben, so wird ihr Herr sie in Seine Barmherzigkeit eingehen lassen.",
    "arabic_full": "فَأَمَّا ٱلَّذِينَ ءَامَنُوا۟ وَعَمِلُوا۟ ٱلصَّـٰلِحَـٰتِ فَيُدْخِلُهُمْ رَبُّهُمْ فِى رَحْمَتِهِۦ ۚ ذَٰلِكَ هُوَ ٱلْفَوْزُ ٱلْمُبِينُ",
    "arabic": "",
    "transcription": "Fa'ammal-lażīna āmanū wa 'amiluṣ-ṣāliḥāti fayudkhiluhum rabbuhum fī raḥmatih(ī),"
  },
  {
    "index": 54,
    "verse_number": 30,
    "translation": "Das ist der deutliche Erfolg.",
    "arabic_full": "فَأَمَّا ٱلَّذِينَ ءَامَنُوا۟ وَعَمِلُوا۟ ٱلصَّـٰلِحَـٰتِ فَيُدْخِلُهُمْ رَبُّهُمْ فِى رَحْمَتِهِۦ ۚ ذَٰلِكَ هُوَ ٱلْفَوْزُ ٱلْمُبِينُ",
    "arabic": "",
    "transcription": "żālika huwal-fauzul-mubīn(u)."
  },
  {
    "index": 55,
    "verse_number": 31,
    "translation": "Was aber diejenigen angeht, die ungläubig waren, so (wird zu ihnen gesagt werden): Sind euch Meine Zeichen nicht stets verlesen worden?",
    "arabic_full": "وَأَمَّا ٱلَّذِينَ كَفَرُوٓا۟ أَفَلَمْ تَكُنْ ءَايَـٰتِى تُتْلَىٰ عَلَيْكُمْ فَٱسْتَكْبَرْتُمْ وَكُنتُمْ قَوْمًا مُّجْرِمِينَ",
    "arabic": "",
    "transcription": "Wa ammal-lażīna kafarū, afalam takun āyātī tutlā 'alaikum"
  },
  {
    "index": 56,
    "verse_number": 31,
    "translation": "Aber ihr habt euch hochmütig verhalten und seid ein Volk von Übeltätern gewesen.",
    "arabic_full": "وَأَمَّا ٱلَّذِينَ كَفَرُوٓا۟ أَفَلَمْ تَكُنْ ءَايَـٰتِى تُتْلَىٰ عَلَيْكُمْ فَٱسْتَكْبَرْتُمْ وَكُنتُمْ قَوْمًا مُّجْرِمِينَ",
    "arabic": "",
    "transcription": "fastakbartum wa kuntum qaumam mujrimīn(a)."
  },
  {
    "index": 57,
    "verse_number": 32,
    "translation": "Und wenn gesagt wurde: .Gewiß, Allahs Versprechen ist wahr,",
    "arabic_full": "وَإِذَا قِيلَ إِنَّ وَعْدَ ٱللَّهِ حَقٌّ وَٱلسَّاعَةُ لَا رَيْبَ فِيهَا قُلْتُم مَّا نَدْرِى مَا ٱلسَّاعَةُ إِن نَّظُنُّ إِلَّا ظَنًّا وَمَا نَحْنُ بِمُسْتَيْقِنِينَ",
    "arabic": "",
    "transcription": "Wa iżā qīla inna wa'dallāhi ḥaqquw"
  },
  {
    "index": 58,
    "verse_number": 32,
    "translation": "und an der Stunde gibt es keinen Zweifel’, sagtet ihr: ,Wir wissen nicht, was die Stunde ist.",
    "arabic_full": "وَإِذَا قِيلَ إِنَّ وَعْدَ ٱللَّهِ حَقٌّ وَٱلسَّاعَةُ لَا رَيْبَ فِيهَا قُلْتُم مَّا نَدْرِى مَا ٱلسَّاعَةُ إِن نَّظُنُّ إِلَّا ظَنًّا وَمَا نَحْنُ بِمُسْتَيْقِنِينَ",
    "arabic": "",
    "transcription": "was-sā'atu lā raiba fīhā qultum mā nadrī mas-sā'ah(tu)"
  },
  {
    "index": 59,
    "verse_number": 32,
    "translation": "Wir stellen ja nur Mutmaßungen an und sind gar nicht überzeugt’.",
    "arabic_full": "وَإِذَا قِيلَ إِنَّ وَعْدَ ٱللَّهِ حَقٌّ وَٱلسَّاعَةُ لَا رَيْبَ فِيهَا قُلْتُم مَّا نَدْرِى مَا ٱلسَّاعَةُ إِن نَّظُنُّ إِلَّا ظَنًّا وَمَا نَحْنُ بِمُسْتَيْقِنِينَ",
    "arabic": "",
    "transcription": "in naẓunnu illā ẓannaw wa mā naḥnu bimustaiqinīn(a)."
  },
  {
    "index": 60,
    "verse_number": 33,
    "translation": "Und es werden ihnen die bösen Taten, die sie vollbracht haben, klar, und es umschließt sie das, worüber sie sich lustig zu machen pflegten.",
    "arabic_full": "وَبَدَا لَهُمْ سَيِّـَٔاتُ مَا عَمِلُوا۟ وَحَاقَ بِهِم مَّا كَانُوا۟ بِهِۦ يَسْتَهْزِءُونَ",
    "arabic": "",
    "transcription": "Wa badā lahum sayyi'ātu mā 'amilū wa ḥāqa bihim mā kānū bihī yastahzi'ūn(a)."
  },
  {
    "index": 61,
    "verse_number": 34,
    "translation": "Und es wird gesagt: Heute werden Wir euch vergessen, wie ihr die Begegnung mit diesem eurem Tag vergessen habt.",
    "arabic_full": "وَقِيلَ ٱلْيَوْمَ نَنسَىٰكُمْ كَمَا نَسِيتُمْ لِقَآءَ يَوْمِكُمْ هَـٰذَا وَمَأْوَىٰكُمُ ٱلنَّارُ وَمَا لَكُم مِّن نَّـٰصِرِينَ",
    "arabic": "",
    "transcription": "Wa qīlal-yauma nansākum kamā nasītum liqā'a yaumikum hāżā"
  },
  {
    "index": 62,
    "verse_number": 34,
    "translation": "Euer Zufluchtsort ist das (Höllen)feuer, und ihr werdet keine Helfer haben.",
    "arabic_full": "وَقِيلَ ٱلْيَوْمَ نَنسَىٰكُمْ كَمَا نَسِيتُمْ لِقَآءَ يَوْمِكُمْ هَـٰذَا وَمَأْوَىٰكُمُ ٱلنَّارُ وَمَا لَكُم مِّن نَّـٰصِرِينَ",
    "arabic": "",
    "transcription": "wa ma'wākumun nāru wa mā lakum min nāṣirīn(a)."
  },
  {
    "index": 63,
    "verse_number": 35,
    "translation": "Dies ist dafür, daß ihr euch über Allahs Zeichen lustig machtet und daß euch das diesseitige Leben täuschte.",
    "arabic_full": "ذَٰلِكُم بِأَنَّكُمُ ٱتَّخَذْتُمْ ءَايَـٰتِ ٱللَّهِ هُزُوًا وَغَرَّتْكُمُ ٱلْحَيَوٰةُ ٱلدُّنْيَا ۚ فَٱلْيَوْمَ لَا يُخْرَجُونَ مِنْهَا وَلَا هُمْ يُسْتَعْتَبُونَ",
    "arabic": "",
    "transcription": "Żālikum bi'annakumuttakhażtum āyātillāhi huzuwaw wa garratkumul-ḥayātud-dun-yā,"
  },
  {
    "index": 64,
    "verse_number": 35,
    "translation": "Heute werden sie nicht (mehr) aus ihm herausgebracht, und es wird ihnen keine Gnade (mehr) erwiesen.",
    "arabic_full": "ذَٰلِكُم بِأَنَّكُمُ ٱتَّخَذْتُمْ ءَايَـٰتِ ٱللَّهِ هُزُوًا وَغَرَّتْكُمُ ٱلْحَيَوٰةُ ٱلدُّنْيَا ۚ فَٱلْيَوْمَ لَا يُخْرَجُونَ مِنْهَا وَلَا هُمْ يُسْتَعْتَبُونَ",
    "arabic": "",
    "transcription": "fal-yauma lā yukhrajūna minhā wa lā hum yusta'tabūn(a)."
  },
  {
    "index": 65,
    "verse_number": 36,
    "translation": "So gehört (alles) Lob Allah, dem Herrn der Himmel und dem Herrn der Erde, dem Herrn der Weltenbewohner’!",
    "arabic_full": "فَلِلَّهِ ٱلْحَمْدُ رَبِّ ٱلسَّمَـٰوَٰتِ وَرَبِّ ٱلْأَرْضِ رَبِّ ٱلْعَـٰلَمِينَ",
    "arabic": "",
    "transcription": "Fa lillāhil-ḥamdu rabbis-samāwāti wa rabbil-arḍi rabbil-'ālamīn(a)."
  },
  {
    "index": 66,
    "verse_number": 37,
    "translation": "Ihm gehört die Oberhoheit in den Himmeln und auf der Erde, und Er ist der Allmächtige und Allweise.",
    "arabic_full": "وَلَهُ ٱلْكِبْرِيَآءُ فِى ٱلسَّمَـٰوَٰتِ وَٱلْأَرْضِ ۖ وَهُوَ ٱلْعَزِيزُ ٱلْحَكِيمُ",
    "arabic": "",
    "transcription": "Wa lahul-kibriyā'u fis-samāwāti wal-arḍ(i), wa huwal-'azīzul-ḥakīm(u)."
  }
]