[
  {
    "verse_number": 56,
    "text_uthmani": "قَالَ وَمَن يَقْنَطُ مِن رَّحْمَةِ رَبِّهِۦٓ إِلَّا ٱلضَّآلُّونَ",
    "text_uthmani_transcribed": "Qāla wa may yaqnaṭu mir raḥmati rabbihī illaḍ-ḍāllūn(a).",
    "translation": "Ведь кто отчаиваться (смеет) в милости Господней, Помимо тех, кто был сведен с Его пути"
  },
  {
    "verse_number": 57,
    "text_uthmani": "قَالَ فَمَا خَطْبُكُمْ أَيُّهَا ٱلْمُرْسَلُونَ",
    "text_uthmani_transcribed": "Qāla famā khaṭbukum ayyuhal-mursalūn(a).",
    "translation": "Так в чем посланничество ваше? - он сказал"
  },
  {
    "verse_number": 58,
    "text_uthmani": "قَالُوٓا۟ إِنَّآ أُرْسِلْنَآ إِلَىٰ قَوْمٍ مُّجْرِمِينَ",
    "text_uthmani_transcribed": "Qālū innā ursilnā ilā qaumim mujrimīn(a).",
    "translation": "Они ответили: \"Мы посланы к народу, погрязшему в грехе"
  },
  {
    "verse_number": 59,
    "text_uthmani": "إِلَّآ ءَالَ لُوطٍ إِنَّا لَمُنَجُّوهُمْ أَجْمَعِينَ",
    "text_uthmani_transcribed": "Illā āla lūṭ(in), innā lamunajjūhum ajma'īn(a).",
    "translation": "Кроме семейства Лута, Всех из которого, поистине, спасем мы"
  },
  {
    "verse_number": 60,
    "text_uthmani": "إِلَّا ٱمْرَأَتَهُۥ قَدَّرْنَآ ۙ إِنَّهَا لَمِنَ ٱلْغَـٰبِرِينَ",
    "text_uthmani_transcribed": "Illamra'atahū qaddarnā innahā laminal-gābirīn(a).",
    "translation": "Кроме жены его, Которой Мы определили быть из тех, Кто позади останется (для понесенья кары)"
  },
  {
    "verse_number": 61,
    "text_uthmani": "فَلَمَّا جَآءَ ءَالَ لُوطٍ ٱلْمُرْسَلُونَ",
    "text_uthmani_transcribed": "Falammā jā'a āla lūṭinil-mursalūn(a).",
    "translation": "Когда же вестники пришли к семейству Лута"
  },
  {
    "verse_number": 62,
    "text_uthmani": "قَالَ إِنَّكُمْ قَوْمٌ مُّنكَرُونَ",
    "text_uthmani_transcribed": "Qāla innakum qaumum munkarūn(a).",
    "translation": "Он сказал: \"Вы мне, поистине, неведомые люди"
  },
  {
    "verse_number": 63,
    "text_uthmani": "قَالُوا۟ بَلْ جِئْنَـٰكَ بِمَا كَانُوا۟ فِيهِ يَمْتَرُونَ",
    "text_uthmani_transcribed": "Qālū bal ji'nāka bimā kānū fīhi yamtarūn(a).",
    "translation": "Они сказали: \"Да, пришли мы с тем, О чем они (так долго) сомневались"
  },
  {
    "verse_number": 64,
    "text_uthmani": "وَأَتَيْنَـٰكَ بِٱلْحَقِّ وَإِنَّا لَصَـٰدِقُونَ",
    "text_uthmani_transcribed": "Wa ataināka bil-ḥaqqi wa innā laṣādiqūn(a).",
    "translation": "И мы к тебе пришли, (чтобы свершилось то), Чему назначено свершиться, И, истинно, мы правду говорим"
  },
  {
    "verse_number": 65,
    "text_uthmani": "فَأَسْرِ بِأَهْلِكَ بِقِطْعٍ مِّنَ ٱلَّيْلِ وَٱتَّبِعْ أَدْبَـٰرَهُمْ وَلَا يَلْتَفِتْ مِنكُمْ أَحَدٌ وَٱمْضُوا۟ حَيْثُ تُؤْمَرُونَ",
    "text_uthmani_transcribed": "Fa asri bi'ahlika biqiṭ'im minal-laili wattabi' adbārahum wa lā yaltafit minkum aḥaduw wamḍū ḥaiṡu tu'marūn(a).",
    "translation": "Ты выведи свою семью, Пока не истекли часы ночные, И позади нее иди, (ей замыкая) тыл, И пусть никто из вас назад не оглянется. Идите так, как вам повелено идти"
  },
  {
    "verse_number": 66,
    "text_uthmani": "وَقَضَيْنَآ إِلَيْهِ ذَٰلِكَ ٱلْأَمْرَ أَنَّ دَابِرَ هَـٰٓؤُلَآءِ مَقْطُوعٌ مُّصْبِحِينَ",
    "text_uthmani_transcribed": "Wa qaḍainā ilaihi żālikal-amra anna dābira hā'ulā'i maqṭū'um muṣbiḥīn(a).",
    "translation": "Мы объявили это повеление ему О том, что с наступлением утра Всем тем, кто позади остался, Быть истребленным надлежит"
  }
]