[
  {
    "verse_number": 23,
    "text_uthmani": "فَوَرَبِّ ٱلسَّمَآءِ وَٱلْأَرْضِ إِنَّهُۥ لَحَقٌّ مِّثْلَ مَآ أَنَّكُمْ تَنطِقُونَ",
    "text_uthmani_transcribed": "Fa wa rabbis-samā'i wal-arḍi innahū laḥaqqum miṡla mā annakum tanṭiqūn(a).",
    "translation": "А потому, клянусь Властителем земли и неба, Сие есть истина такая же, как та, Что вы разумно обращаетесь друг к другу"
  },
  {
    "verse_number": 24,
    "text_uthmani": "هَلْ أَتَىٰكَ حَدِيثُ ضَيْفِ إِبْرَٰهِيمَ ٱلْمُكْرَمِينَ",
    "text_uthmani_transcribed": "Hal atāka ḥadīṡu ḍaifi ibrāhīmal-mukramīn(a).",
    "translation": "К тебе пришел рассказ об Ибрахиме И почитаемых его гостях"
  },
  {
    "verse_number": 25,
    "text_uthmani": "إِذْ دَخَلُوا۟ عَلَيْهِ فَقَالُوا۟ سَلَـٰمًا ۖ قَالَ سَلَـٰمٌ قَوْمٌ مُّنكَرُونَ",
    "text_uthmani_transcribed": "Iż dakhalū 'alaihi fa qālū salāmā(n), qāla salām(un), qaumum munkarūn(a).",
    "translation": "Итак, они вошли к нему и молвили: \"Мир (вам)\". Он им ответил: \"Мир\". (А сам подумал): \"Как необычны эти люди"
  },
  {
    "verse_number": 26,
    "text_uthmani": "فَرَاغَ إِلَىٰٓ أَهْلِهِۦ فَجَآءَ بِعِجْلٍ سَمِينٍ",
    "text_uthmani_transcribed": "Farāga ilā ahlihī fa jā'a bi'ijlin samīn(in).",
    "translation": "Затем он быстро вышел к домочадцам И вынес мясо сочное теленка"
  },
  {
    "verse_number": 27,
    "text_uthmani": "فَقَرَّبَهُۥٓ إِلَيْهِمْ قَالَ أَلَا تَأْكُلُونَ",
    "text_uthmani_transcribed": "Fa qarrabahū ilaihim, qāla alā ta'kulūn(a).",
    "translation": "И, положив его пред ними, сказал: \"Быть может, поедите вы"
  },
  {
    "verse_number": 28,
    "text_uthmani": "فَأَوْجَسَ مِنْهُمْ خِيفَةً ۖ قَالُوا۟ لَا تَخَفْ ۖ وَبَشَّرُوهُ بِغُلَـٰمٍ عَلِيمٍ",
    "text_uthmani_transcribed": "Fa aujasa minhum khīfah(tan), qālū lā takhaf, wa basysyarūhu bigulāmin 'alīm(in).",
    "translation": "(Когда ж они отведать пищу отказались), В нем страх проснулся к ним. Но молвили они: \"Не бойся!\" И сообщили ему радостную весть О мудром мальчике-младенце"
  },
  {
    "verse_number": 29,
    "text_uthmani": "فَأَقْبَلَتِ ٱمْرَأَتُهُۥ فِى صَرَّةٍ فَصَكَّتْ وَجْهَهَا وَقَالَتْ عَجُوزٌ عَقِيمٌ",
    "text_uthmani_transcribed": "Fa aqbalatimra'atuhū fī ṣarratin fa ṣakkat wajhahā wa qālat 'ajūzun 'aqīm(un).",
    "translation": "Но тут жена его вперед вступила И, стукнув в изумлении себя по лбу, Воскликнула: \"Ведь я неплодная старуха"
  },
  {
    "verse_number": 30,
    "text_uthmani": "قَالُوا۟ كَذَٰلِكِ قَالَ رَبُّكِ ۖ إِنَّهُۥ هُوَ ٱلْحَكِيمُ ٱلْعَلِيمُ",
    "text_uthmani_transcribed": "Qālū każālik(i), qāla rabbuk(i), innahū huwal-ḥakīmul-'alīm(u).",
    "translation": "(На что) ответили они: \"Так говорит Господь ваш, А Он, поистине, и мудрости, и знания исполнен"
  },
  {
    "verse_number": 31,
    "text_uthmani": "۞ قَالَ فَمَا خَطْبُكُمْ أَيُّهَا ٱلْمُرْسَلُونَ",
    "text_uthmani_transcribed": "Qāla famā khaṭbukum ayyuhal-mursalūn(a).",
    "translation": "И Ибрахим сказал: \"В чем ваша миссия, посланники, сейчас"
  },
  {
    "verse_number": 32,
    "text_uthmani": "قَالُوٓا۟ إِنَّآ أُرْسِلْنَآ إِلَىٰ قَوْمٍ مُّجْرِمِينَ",
    "text_uthmani_transcribed": "Qālū innā ursilnā ilā qaumim mujrimīn(a).",
    "translation": "Они ответили: \"Мы посланы к народу, погрязшему в грехе"
  },
  {
    "verse_number": 33,
    "text_uthmani": "لِنُرْسِلَ عَلَيْهِمْ حِجَارَةً مِّن طِينٍ",
    "text_uthmani_transcribed": "Linursila 'alaihim ḥijāratam min ṭīn(in).",
    "translation": "Чтоб их камнями забросать из глины"
  }
]