[
  {
    "verse_number": 1,
    "translation": "Preise den Namen deines höchsten Herrn,"
  },
  {
    "verse_number": 2,
    "translation": "Der erschafft und dann zurechtformt"
  },
  {
    "verse_number": 3,
    "translation": "und Der das Maß festsetzt und dann rechtleitet"
  },
  {
    "verse_number": 4,
    "translation": "und Der die Weide hervorbringt"
  },
  {
    "verse_number": 5,
    "translation": "und sie dann zu dunkelbrauner Spreu macht."
  },
  {
    "verse_number": 6,
    "translation": "Wir werden dich lesen lassen, und dann wirst du nichts vergessen,"
  },
  {
    "verse_number": 7,
    "translation": "außer dem, was Allah will. Er weiß ja, was laut vernehmbar geäußert wird und was verborgen bleibt."
  },
  {
    "verse_number": 8,
    "translation": "Und Wir werden dir den Weg zum Leichteren leicht machen."
  },
  {
    "verse_number": 9,
    "translation": "So ermahne -, wenn die Ermahnung nützt."
  },
  {
    "verse_number": 10,
    "translation": "Bedenken wird jemand, der gottesfürchtig ist."
  },
  {
    "verse_number": 11,
    "translation": "Meiden aber wird es der Unseligste,"
  },
  {
    "verse_number": 12,
    "translation": "der dem größten (Höllen)feuer ausgesetzt sein wird;"
  },
  {
    "verse_number": 13,
    "translation": "darin wird er hierauf weder sterben noch leben."
  },
  {
    "verse_number": 14,
    "translation": "Wohl ergehen wird es ja jemandem, der sich läutert,"
  },
  {
    "verse_number": 15,
    "translation": "und des Namens seines Herrn gedenkt; so betet er."
  },
  {
    "verse_number": 16,
    "translation": "Nein! Vielmehr zieht ihr das diesseitige Leben vor,"
  },
  {
    "verse_number": 17,
    "translation": "während das Jenseits besser und beständiger ist."
  },
  {
    "verse_number": 18,
    "translation": "Dies ist wahrlich in den früheren Blättern (enthalten),"
  },
  {
    "verse_number": 19,
    "translation": "den Blättern Ibrahims und Musas."
  }
]